ipfs_cid/__init__.py
ipfs_cid/base32.py
ipfs_cid/encode.py
ipfs_cid-0.2.0.dist-info/LICENSE.md
ipfs_cid-0.2.0.dist-info/METADATA
ipfs_cid-0.2.0.dist-info/WHEEL
ipfs_cid-0.2.0.dist-info/RECORD
