Metadata-Version: 2.1
Name: ipfs-cid
Version: 0.2.0
Summary: A library for building IPFS CID v1 compatible content identifiers using fixed encoding parameters.
Home-page: https://github.com/thunderstore-io/ipfs-cid
License: MIT
Keywords: ipfs,multihash,multibase,cid,hash
Author: Mythic
Author-email: mythic@thunderstore.io
Requires-Python: >=3.8,<4.0
Classifier: License :: OSI Approved :: MIT License
Classifier: Programming Language :: Python :: 3
Classifier: Programming Language :: Python :: 3.8
Classifier: Programming Language :: Python :: 3.9
Classifier: Programming Language :: Python :: 3.10
Classifier: Programming Language :: Python :: 3.11
Project-URL: Repository, https://github.com/thunderstore-io/ipfs-cid
